{"nameZh": "\u9f8d\u606f", "nameJp": "\u308a\u3085\u3046\u306e\u3044\u3076\u304d", "nameEn": "Dragon Breath", "type": "\u9f8d", "category": "Special", "power": 60, "accuracy": 100, "PP": 20, "description": "\u5c07\u5f37\u70c8\u7684\u6c23\u606f\u5439\u5411\u5c0d\u624b\u9032\u884c\u653b\u64ca\u3002\u6709\u6642\u6703\u8b93\u5c0d\u624b\u9677\u5165\u9ebb\u75fa\u72c0\u614b\u3002", "levelingUps": [{"level": 20, "link": "841"}, {"level": 12, "link": "443"}, {"level": 0, "link": "444"}, {"level": 0, "link": "445"}, {"level": 10, "link": "704"}, {"level": 0, "link": "705"}, {"level": 0, "link": "706"}, {"level": 20, "link": "333"}, {"level": 20, "link": "334"}, {"level": 10, "link": "371"}, {"level": 0, "link": "372"}, {"level": 0, "link": "373"}, {"level": 0, "link": "887"}, {"level": 4, "link": "633"}, {"level": 0, "link": "634"}, {"level": 0, "link": "635"}, {"level": 21, "link": "990"}, {"level": 12, "link": "949"}, {"level": 12, "link": "950"}, {"level": 12, "link": "951"}, {"level": 0, "link": "985"}, {"level": 0, "link": "999"}, {"level": 12, "link": "004"}, {"level": 12, "link": "005"}, {"level": 12, "link": "006"}]}