{"nameZh": "\u7948\u9858", "nameJp": "\u306d\u304c\u3044\u3054\u3068", "nameEn": "Wish", "type": "Normal", "category": "Status", "power": 0, "accuracy": 0, "PP": 10, "description": "\u5728\u4e0b\u4e00\u56de\u5408\u56de\u5fa9\u81ea\u5df1\u6216\u662f\u66ff\u63db\u4e0a\u5834\u7684\u5bf6\u53ef\u5922\u6700\u5927\uff28\uff30\u7684\u4e00\u534a\u3002", "levelingUps": [{"level": 28, "link": "282"}, {"level": 20, "link": "669"}, {"level": 20, "link": "670"}, {"level": 0, "link": "671"}, {"level": 13, "link": "370"}, {"level": 37, "link": "594"}, {"level": 70, "link": "985"}, {"level": 28, "link": "987"}], "technicalMachine": null, "eggPokemons": ["921", "922", "923", "174", "039", "040", "172", "025", "926", "927", "026", "133", "134", "135", "136", "196", "197", "470", "471", "700", "203", "981", "775", "026-a", "653", "654", "655"]}