{"nameZh": "\u5927\u6674\u5929", "nameJp": "\u306b\u307b\u3093\u3070\u308c", "nameEn": "Sunny Day", "type": "\u706b", "category": "Status", "power": 0, "accuracy": 0, "PP": 5, "description": "\u8b93\u967d\u5149\u589e\u5f37\uff0c\u5728\uff15\u56de\u5408\u5167\u63d0\u9ad8\u706b\u5c6c\u6027\u62db\u5f0f\u7684\u5a01\u529b\u3002\u6c34\u5c6c\u6027\u62db\u5f0f\u7684\u5a01\u529b\u6703\u964d\u4f4e\u3002", "levelingUps": [{"level": 36, "link": "191"}, {"level": 39, "link": "192"}, {"level": 36, "link": "548"}, {"level": 0, "link": "549"}, {"level": 0, "link": "437"}, {"level": 35, "link": "470"}, {"level": 45, "link": "753"}, {"level": 51, "link": "754"}, {"level": 17, "link": "938"}, {"level": 17, "link": "939"}, {"level": 0, "link": "978"}, {"level": -2, "link": "982"}, {"level": -2, "link": "979"}, {"level": -2, "link": "983"}, {"level": -2, "link": "984"}, {"level": -2, "link": "981"}, {"level": -2, "link": "985"}, {"level": 0, "link": "998"}]}