{"nameZh": "\u80fd\u91cf\u7403", "nameJp": "\u30a8\u30ca\u30b8\u30fc\u30dc\u30fc\u30eb", "nameEn": "Energy Ball", "type": "\u8349", "category": "Special", "power": 90, "accuracy": 100, "PP": 10, "description": "\u767c\u5c04\u5f9e\u5927\u81ea\u7136\u532f\u805a\u800c\u4f86\u7684\u751f\u547d\u529b\u91cf\u3002\u6709\u6642\u6703\u964d\u4f4e\u5c0d\u624b\u7684\u7279\u9632\u3002", "levelingUps": [{"level": 32, "link": "906"}, {"level": 38, "link": "907"}, {"level": 42, "link": "908"}, {"level": 30, "link": "935"}, {"level": 34, "link": "936"}, {"level": 34, "link": "937"}, {"level": 30, "link": "548"}, {"level": 0, "link": "549"}, {"level": 44, "link": "842"}, {"level": 28, "link": "585"}, {"level": 28, "link": "586"}, {"level": 42, "link": "331"}, {"level": 44, "link": "332"}]}