{"nameZh": "\u5ca9\u5d29", "nameJp": "\u3044\u308f\u306a\u3060\u308c", "nameEn": "Rock Slide", "type": "Rock", "category": "Physical", "power": 75, "accuracy": 90, "PP": 10, "description": "\u5c07\u5927\u5ca9\u77f3\u731b\u70c8\u5730\u7838\u5411\u5c0d\u624b\u9032\u884c\u653b\u64ca\u3002\u6709\u6642\u6703\u8b93\u5c0d\u624b\u754f\u7e2e\u3002", "levelingUps": [{"level": 32, "link": "438"}, {"level": 32, "link": "185"}, {"level": 32, "link": "744"}, {"level": 32, "link": "744-d"}, {"level": 36, "link": "745"}, {"level": 36, "link": "745-m"}, {"level": 36, "link": "745-d"}, {"level": 30, "link": "932"}, {"level": 34, "link": "933"}, {"level": 34, "link": "934"}, {"level": -1, "link": "323"}, {"level": 42, "link": "950"}, {"level": 47, "link": "962"}, {"level": 33, "link": "969"}, {"level": 33, "link": "970"}, {"level": 15, "link": "246"}, {"level": 15, "link": "247"}, {"level": 15, "link": "248"}, {"level": 36, "link": "874"}, {"level": 42, "link": "995"}, {"level": 60, "link": "1003"}, {"level": 35, "link": "703"}, {"level": 36, "link": "900"}, {"level": 48, "link": "058-h"}, {"level": 0, "link": "059-h"}, {"level": -1, "link": "713-h"}], "technicalMachine": {"pid": 86, "leaguePoint": 5000, "material": "\u9e7d\u77f3\u5bf6\u7684\u9e7dx3;\u5ca9\u72d7\u72d7\u7684\u5ca9x3;\u76c6\u624d\u602a\u7684\u773c\u6ddax3", "pokemon": ["705", "088", "089", "128-p", "128-b", "128-a", "088-a", "089-a", "706", "113", "050", "051", "242", "194-p", "194", "980", "834", "475", "287", "289", "438", "185", "744", "745", "837", "838", "839", "745-m", "286", "296", "297", "739", "740", "231", "232", "878", "879", "443", "444", "445", "932", "933", "934", "324", "322", "323", "436", "437", "612", "056", "057", "979", "307", "308", "447", "448", "339", "340", "704", "453", "454", "206", "982", "216", "217", "335", "672", "673", "574", "575", "576", "950", "204", "205", "214", "449", "450", "551", "552", "553", "843", "844", "749", "750", "371", "372", "373", "957", "958", "959", "962", "968", "870", "701", "969", "970", "765", "766", "775", "246", "247", "248", "874", "769", "770", "199", "422", "423", "692", "693", "604", "149", "460", "613", "614", "712", "713", "627", "628", "635", "977", "984", "990", "992", "995", "1003", "1005", "745-d", "288", "744-d", "004", "005", "006", "195", "656", "657", "658", "157", "650", "651", "652", "903", "703", "900", "901", "128", "050-a", "051-a", "705-h", "706-h", "058-h", "059-h", "713-h", "157-h", "150", "151", "382", "383", "384", "483", "484", "485", "493"]}, "eggPokemons": []}