{"levelingUps": [], "egg": [], "TM": {"materials": [{"part": "\u5343\u91dd\u9b5a\u7684\u523a", "count": 8, "link": 211}, {"part": "\u5403\u543c\u9738\u7684\u9b0d\u9b1a", "count": 5, "link": 977}, {"part": "\u611b\u5fc3\u9b5a\u7684\u9c57\u7247", "count": 3, "link": 370}], "pid": 154, "leaguePoint": 14000, "pm": [{"types": ["\u6c34"], "link": "9", "nameZh": "\u6c34\u7bad\u9f9c", "altForm": null}, {"types": ["\u8d85\u80fd\u529b"], "link": "151", "nameZh": "\u5922\u5e7b", "altForm": null}, {"types": ["\u6c34"], "link": "160", "nameZh": "\u5927\u529b\u9c77", "altForm": null}, {"types": ["\u6c34", "\u5730\u9762"], "link": "260", "nameZh": "\u5de8\u6cbc\u602a", "altForm": null}, {"types": ["\u6c34", "\u92fc"], "link": "395", "nameZh": "\u5e1d\u738b\u62ff\u6ce2", "altForm": null}, {"types": ["\u6c34"], "link": "503", "nameZh": "\u5927\u528d\u9b3c", "altForm": null}, {"types": ["\u6c34", "\u60e1"], "link": "503-1", "nameZh": "\u5927\u528d\u9b3c", "altForm": "\u6d17\u7fe0"}, {"types": ["\u6c34", "\u60e1"], "link": "658", "nameZh": "\u7532\u8cc0\u5fcd\u86d9", "altForm": ""}, {"types": ["\u6c34", "\u60e1"], "link": "658-1", "nameZh": "\u7532\u8cc0\u5fcd\u86d9", "altForm": "\u5c0f\u667a"}, {"types": ["\u6c34", "\u5996\u7cbe"], "link": "730", "nameZh": "\u897f\u7345\u6d77\u58ec", "altForm": null}, {"types": ["\u6c34"], "link": "818", "nameZh": "\u5343\u9762\u907f\u5f79", "altForm": null}, {"types": ["\u6c34", "\u683c\u9b25"], "link": "914", "nameZh": "\u72c2\u6b61\u6d6a\u821e\u9d28", "altForm": null}]}, "pid": 308, "nameZh": "\u52a0\u8fb2\u6c34\u70ae", "nameJp": "\u30cf\u30a4\u30c9\u30ed\u30ab\u30ce\u30f3", "nameEn": "Hydro Cannon", "type": "\u6c34", "category": "\u7279\u6b8a", "power": 150, "accuracy": 90, "PP": 5, "description": "\u5411\u5c0d\u624b\u767c\u5c04\u6c34\u70ae\u9032\u884c\u653b\u64ca\u3002\u4e0b\u4e00\u56de\u5408\u81ea\u5df1\u5c07\u7121\u6cd5\u52d5\u5f48\u3002"}