{"levelingUps": [{"types": ["\u8d85\u80fd\u529b"], "link": "150", "nameZh": "\u8d85\u5922", "altForm": null, "level": 72}], "egg": [], "pid": 540, "nameZh": "\u7cbe\u795e\u64ca\u7834", "nameJp": "\u30b5\u30a4\u30b3\u30d6\u30ec\u30a4\u30af", "nameEn": "Psystrike", "type": "\u8d85\u80fd\u529b", "category": "\u7279\u6b8a", "power": 100, "accuracy": 100, "PP": 10, "description": "\u5c07\u795e\u5947\u7684\u5ff5\u529b\u6ce2\u5be6\u9ad4\u5316\u5f8c\u653b\u64ca\u5c0d\u624b\u3002\u7d66\u4e88\u5c0d\u624b\u7269\u7406\u50b7\u5bb3\u3002"}