{"levelingUps": [{"types": ["\u8349", "\u9f8d"], "link": "1011", "nameZh": "\u88f9\u871c\u87f2", "altForm": null, "level": 28}], "egg": [], "pid": 903, "nameZh": "\u7cd6\u6f3f\u70b8\u5f48", "nameJp": "\u307f\u305a\u3042\u3081\u30dc\u30e0", "nameEn": "Syrup Bomb", "type": "\u8349", "category": "\u7279\u6b8a", "power": 60, "accuracy": 85, "PP": 10, "description": "\u4f7f\u9ecf\u7a20\u7684\u7cd6\u6f3f\u7206\u70b8\uff0c\u4f7f\u5c0d\u624b\u9677\u5165\u6eff\u8eab\u7cd6\u72c0\u614b\uff0c\u5728\uff13\u56de\u5408\u5167\u6301\u7e8c\u964d\u4f4e\u5c0d\u624b\u7684\u901f\u5ea6\u3002"}