{"pid": 662, "link": "662", "paldea": 20, "kitakami": null, "hisui": null, "nameZh": "\u706b\u7bad\u96c0", "nameJp": "\u30d2\u30ce\u30e4\u30b3\u30de", "nameEn": "Fletchinder", "altForm": null, "hiddenAbility": "\u75be\u98a8\u4e4b\u7ffc", "baseStatsTotal": 382, "genderRatio": 127, "source": "661", "types": ["\u706b", "\u98db\u884c"], "abilities": ["\u706b\u7130\u4e4b\u8ec0"], "baseStats": [62, 73, 55, 56, 52, 84], "EVs": [0, 0, 0, 0, 0, 2], "moves": {"levelingUps": [{"level": 0, "pid": 488, "nameZh": "\u84c4\u80fd\u7130\u8972", "nameJp": "\u30cb\u30c8\u30ed\u30c1\u30e3\u30fc\u30b8", "nameEn": "Flame Charge", "type": "\u706b", "category": "\u7269\u7406", "power": 50, "accuracy": 100, "PP": 20, "description": "\u8b93\u706b\u7130\u570d\u7e5e\u5168\u8eab\u5f8c\u653b\u64ca\u5c0d\u624b\u3002\u540c\u6642\u84c4\u7a4d\u529b\u91cf\u4f86\u63d0\u9ad8\u81ea\u5df1\u7684\u901f\u5ea6\u3002"}, {"level": 1, "pid": 45, "nameZh": "\u53eb\u8072", "nameJp": "\u306a\u304d\u3054\u3048", "nameEn": "Growl", "type": "\u4e00\u822c", "category": "\u8b8a\u5316", "power": 0, "accuracy": 100, "PP": 40, "description": "\u767c\u51fa\u53ef\u611b\u7684\u53eb\u8072\uff0c\u8a98\u4f7f\u5c0d\u624b\u758f\u5ffd\u5927\u610f\uff0c\u964d\u4f4e\u5c0d\u624b\u7684\u653b\u64ca\u3002"}, {"level": 1, "pid": 52, "nameZh": "\u706b\u82b1", "nameJp": "\u3072\u306e\u3053", "nameEn": "Ember", "type": "\u706b", "category": "\u7279\u6b8a", "power": 40, "accuracy": 100, "PP": 25, "description": "\u5411\u5c0d\u624b\u767c\u5c04\u5c0f\u706b\u7130\u9032\u884c\u653b\u64ca\u3002\u6709\u6642\u6703\u8b93\u5c0d\u624b\u9677\u5165\u707c\u50b7\u72c0\u614b\u3002"}, {"level": 1, "pid": 64, "nameZh": "\u5544", "nameJp": "\u3064\u3064\u304f", "nameEn": "Peck", "type": "\u98db\u884c", "category": "\u7269\u7406", "power": 35, "accuracy": 100, "PP": 35, "description": "\u7528\u5c16\u92b3\u7684\u5599\u6216\u89d2\u523a\u5411\u5c0d\u624b\u9032\u884c\u653b\u64ca\u3002"}, {"level": 1, "pid": 98, "nameZh": "\u96fb\u5149\u4e00\u9583", "nameJp": "\u3067\u3093\u3053\u3046\u305b\u3063\u304b", "nameEn": "Quick Attack", "type": "\u4e00\u822c", "category": "\u7269\u7406", "power": 40, "accuracy": 100, "PP": 30, "description": "\u4ee5\u8fc5\u96f7\u4e0d\u53ca\u63a9\u8033\u4e4b\u52e2\u64b2\u5411\u5c0d\u624b\u3002\u5fc5\u5b9a\u80fd\u5920\u767c\u52d5\u5148\u5236\u653b\u64ca\u3002"}, {"level": 1, "pid": 364, "nameZh": "\u4f6f\u653b", "nameJp": "\u30d5\u30a7\u30a4\u30f3\u30c8", "nameEn": "Feint", "type": "\u4e00\u822c", "category": "\u7269\u7406", "power": 30, "accuracy": 100, "PP": 10, "description": "\u80fd\u5920\u653b\u64ca\u4f7f\u7528\u4e86\u5b88\u4f4f\u6216\u770b\u7a7f\u7684\u5c0d\u624b\u3002\u4e26\u89e3\u9664\u5c0d\u624b\u7684\u9632\u5b88\u6548\u679c\u3002"}, {"level": 15, "pid": 175, "nameZh": "\u6293\u72c2", "nameJp": "\u3058\u305f\u3070\u305f", "nameEn": "Flail", "type": "\u4e00\u822c", "category": "\u7269\u7406", "power": -1, "accuracy": 100, "PP": 15, "description": "\u6293\u72c2\u822c\u4e82\u6253\u9032\u884c\u653b\u64ca\u3002\u81ea\u5df1\u7684\uff28\uff30\u8d8a\u5c11\uff0c\u62db\u5f0f\u7684\u5a01\u529b\u8d8a\u5927\u3002"}, {"level": 22, "pid": 512, "nameZh": "\u96dc\u6280", "nameJp": "\u30a2\u30af\u30ed\u30d0\u30c3\u30c8", "nameEn": "Acrobatics", "type": "\u98db\u884c", "category": "\u7269\u7406", "power": 55, "accuracy": 100, "PP": 15, "description": "\u8f15\u5de7\u5730\u653b\u64ca\u5c0d\u624b\u3002\u81ea\u5df1\u6c92\u6709\u651c\u5e36\u9053\u5177\u6642\uff0c\u80fd\u7d66\u4e88\u5c0d\u624b\u8f03\u5927\u7684\u50b7\u5bb3\u3002"}, {"level": 29, "pid": 97, "nameZh": "\u9ad8\u901f\u79fb\u52d5", "nameJp": "\u3053\u3046\u305d\u304f\u3044\u3069\u3046", "nameEn": "Agility", "type": "\u8d85\u80fd\u529b", "category": "\u8b8a\u5316", "power": 0, "accuracy": 0, "PP": 30, "description": "\u653e\u9b06\u8eab\u9ad4\uff0c\u8b93\u81ea\u5df1\u8b8a\u5f97\u8f15\u76c8\u4ee5\u9032\u884c\u9ad8\u901f\u79fb\u52d5\u3002\u53ef\u5927\u5e45\u63d0\u9ad8\u81ea\u5df1\u7684\u901f\u5ea6\u3002"}, {"level": 36, "pid": 332, "nameZh": "\u71d5\u8fd4", "nameJp": "\u3064\u3070\u3081\u304c\u3048\u3057", "nameEn": "Aerial Ace", "type": "\u98db\u884c", "category": "\u7269\u7406", "power": 60, "accuracy": 0, "PP": 20, "description": "\u4ee5\u654f\u6377\u7684\u52d5\u4f5c\u6232\u5f04\u5c0d\u624b\u5f8c\u9032\u884c\u5207\u65ac\u3002\u653b\u64ca\u5fc5\u5b9a\u6703\u547d\u4e2d\u3002"}, {"level": 43, "pid": 366, "nameZh": "\u9806\u98a8", "nameJp": "\u304a\u3044\u304b\u305c", "nameEn": "Tailwind", "type": "\u98db\u884c", "category": "\u8b8a\u5316", "power": 0, "accuracy": 0, "PP": 15, "description": "\u522e\u8d77\u731b\u70c8\u7684\u5f37\u98a8\uff0c\u5728\uff14\u56de\u5408\u5167\u63d0\u9ad8\u6211\u65b9\u5168\u9ad4\u7684\u901f\u5ea6\u3002"}, {"level": 50, "pid": 211, "nameZh": "\u92fc\u7ffc", "nameJp": "\u306f\u304c\u306d\u306e\u3064\u3070\u3055", "nameEn": "Steel Wing", "type": "\u92fc", "category": "\u7269\u7406", "power": 70, "accuracy": 90, "PP": 25, "description": "\u7528\u5805\u786c\u7684\u7fc5\u8180\u649e\u64ca\u5c0d\u624b\u9032\u884c\u653b\u64ca\u3002\u6709\u6642\u6703\u63d0\u9ad8\u81ea\u5df1\u7684\u9632\u79a6\u3002"}, {"level": 57, "pid": 355, "nameZh": "\u7fbd\u68f2", "nameJp": "\u306f\u306d\u3084\u3059\u3081", "nameEn": "Roost", "type": "\u98db\u884c", "category": "\u8b8a\u5316", "power": 0, "accuracy": 0, "PP": 5, "description": "\u964d\u843d\u5230\u5730\u9762\uff0c\u8b93\u8eab\u9ad4\u4f11\u606f\u3002\u56de\u5fa9\u81ea\u5df1\u6700\u5927\uff28\uff30\u7684\u4e00\u534a\u3002"}, {"level": 64, "pid": 19, "nameZh": "\u98db\u7fd4", "nameJp": "\u305d\u3089\u3092\u3068\u3076", "nameEn": "Fly", "type": "\u98db\u884c", "category": "\u7269\u7406", "power": 90, "accuracy": 95, "PP": 15, "description": "\u4f7f\u7528\u5f8c\u7684\u7b2c\uff11\u56de\u5408\u98db\u4e0a\u5929\u7a7a\uff0c\u4e26\u65bc\u7b2c\uff12\u56de\u5408\u653b\u64ca\u5c0d\u624b\u3002"}], "eggMoves": [], "TMs": [{"TMPid": 1, "leaguePoint": 400, "pid": 36, "nameZh": "\u731b\u649e", "nameJp": "\u3068\u3063\u3057\u3093", "nameEn": "Take Down", "type": "\u4e00\u822c", "category": "\u7269\u7406", "power": 90, "accuracy": 85, "PP": 20, "description": "\u4ee5\u9a5a\u4eba\u7684\u6c23\u52e2\u649e\u5411\u5c0d\u624b\u9032\u884c\u653b\u64ca\u3002\u81ea\u5df1\u4e5f\u6703\u53d7\u5230\u5c11\u8a31\u50b7\u5bb3\u3002", "materials": [{"material": "\u611b\u5403\u8c5a\u7684\u6bdb", "count": 3, "pm": "915"}, {"material": "\u8c93\u9f2c\u5c11\u7684\u6bdb", "count": 3, "pm": "734"}]}, {"TMPid": 4, "leaguePoint": 800, "pid": 97, "nameZh": "\u9ad8\u901f\u79fb\u52d5", "nameJp": "\u3053\u3046\u305d\u304f\u3044\u3069\u3046", "nameEn": "Agility", "type": "\u8d85\u80fd\u529b", "category": "\u8b8a\u5316", "power": 0, "accuracy": 0, "PP": 30, "description": "\u653e\u9b06\u8eab\u9ad4\uff0c\u8b93\u81ea\u5df1\u8b8a\u5f97\u8f15\u76c8\u4ee5\u9032\u884c\u9ad8\u901f\u79fb\u52d5\u3002\u53ef\u5927\u5e45\u63d0\u9ad8\u81ea\u5df1\u7684\u901f\u5ea6\u3002", "materials": [{"material": "\u5c0f\u7bad\u96c0\u7684\u7fbd\u6bdb", "count": 3, "pm": "661"}, {"material": "\u82b1\u821e\u9ce5\u7684\u7fbd\u6bdb", "count": 3, "pm": "741"}]}, {"TMPid": 7, "leaguePoint": 400, "pid": 182, "nameZh": "\u5b88\u4f4f", "nameJp": "\u307e\u3082\u308b", "nameEn": "Protect", "type": "\u4e00\u822c", "category": "\u8b8a\u5316", "power": 0, "accuracy": 0, "PP": 10, "description": "\u5b8c\u5168\u9632\u4f4f\u5c0d\u624b\u7684\u6240\u6709\u653b\u64ca\u3002\u9023\u7e8c\u4f7f\u7528\u6642\u5bb9\u6613\u5931\u6557\u3002", "materials": [{"material": "\u611b\u5403\u8c5a\u7684\u6bdb", "count": 3, "pm": "915"}, {"material": "\u7c89\u8776\u87f2\u7684\u7c89", "count": 3, "pm": "664"}]}, {"TMPid": 14, "leaguePoint": 3000, "pid": 512, "nameZh": "\u96dc\u6280", "nameJp": "\u30a2\u30af\u30ed\u30d0\u30c3\u30c8", "nameEn": "Acrobatics", "type": "\u98db\u884c", "category": "\u7269\u7406", "power": 55, "accuracy": 100, "PP": 15, "description": "\u8f15\u5de7\u5730\u653b\u64ca\u5c0d\u624b\u3002\u81ea\u5df1\u6c92\u6709\u651c\u5e36\u9053\u5177\u6642\uff0c\u80fd\u7d66\u4e88\u5c0d\u624b\u8f03\u5927\u7684\u50b7\u5bb3\u3002", "materials": [{"material": "\u96fb\u6d77\u71d5\u7684\u7fbd\u6bdb", "count": 3, "pm": "940"}, {"material": "\u4e0b\u77f3\u9ce5\u7684\u7fbd\u6bdb", "count": 3, "pm": "962"}]}, {"TMPid": 18, "leaguePoint": 3000, "pid": 168, "nameZh": "\u5c0f\u5077", "nameJp": "\u3069\u308d\u307c\u3046", "nameEn": "Thief", "type": "\u60e1", "category": "\u7269\u7406", "power": 60, "accuracy": 100, "PP": 25, "description": "\u5728\u653b\u64ca\u7684\u540c\u6642\u5077\u53d6\u9053\u5177\u3002\u7576\u5bf6\u53ef\u5922\u81ea\u5df1\u6709\u651c\u5e36\u9053\u5177\u6642\uff0c\u5247\u7121\u6cd5\u5077\u53d6\u3002", "materials": [{"material": "\u6234\u9b6f\u6bd4\u7684\u7259", "count": 3, "pm": "228"}, {"material": "\u6ecb\u6c41\u9f34\u7684\u58a8\u6c41", "count": 3, "pm": "944"}]}, {"TMPid": 24, "leaguePoint": 800, "pid": 83, "nameZh": "\u706b\u7130\u65cb\u6e26", "nameJp": "\u307b\u306e\u304a\u306e\u3046\u305a", "nameEn": "Fire Spin", "type": "\u706b", "category": "\u7279\u6b8a", "power": 35, "accuracy": 85, "PP": 15, "description": "\u5c07\u5c0d\u624b\u56f0\u5728\u718a\u718a\u71c3\u71d2\u7684\u706b\u7130\u65cb\u6e26\u4e2d\uff0c\u5728\uff14\uff5e\uff15\u56de\u5408\u5167\u9032\u884c\u653b\u64ca\u3002", "materials": [{"material": "\u5361\u8482\u72d7\u7684\u6bdb", "count": 3, "pm": "58"}, {"material": "\u7164\u70ad\u9f9c\u7684\u7164\u70ad", "count": 3, "pm": "324"}]}, {"TMPid": 25, "leaguePoint": 5000, "pid": 263, "nameZh": "\u786c\u6490", "nameJp": "\u304b\u3089\u3052\u3093\u304d", "nameEn": "Facade", "type": "\u4e00\u822c", "category": "\u7269\u7406", "power": 70, "accuracy": 100, "PP": 20, "description": "\u7576\u81ea\u5df1\u9677\u5165\u4e2d\u6bd2\u3001\u9ebb\u75fa\u3001\u707c\u50b7\u7b49\u72c0\u614b\u6642\uff0c\u5411\u5c0d\u624b\u4f7f\u7528\u6b64\u62db\u5f0f\uff0c\u5a01\u529b\u6703\u8b8a\u6210\uff12\u500d\u3002", "materials": [{"material": "\u6a39\u6795\u5c3e\u718a\u7684\u722a\u5b50", "count": 3, "pm": "775"}, {"material": "\u5c0f\u935b\u5320\u7684\u6bdb", "count": 3, "pm": "957"}, {"material": "\u9a5a\u89d2\u9e7f\u7684\u6bdb", "count": 3, "pm": "234"}]}, {"TMPid": 27, "leaguePoint": 800, "pid": 332, "nameZh": "\u71d5\u8fd4", "nameJp": "\u3064\u3070\u3081\u304c\u3048\u3057", "nameEn": "Aerial Ace", "type": "\u98db\u884c", "category": "\u7269\u7406", "power": 60, "accuracy": 0, "PP": 20, "description": "\u4ee5\u654f\u6377\u7684\u52d5\u4f5c\u6232\u5f04\u5c0d\u624b\u5f8c\u9032\u884c\u5207\u65ac\u3002\u653b\u64ca\u5fc5\u5b9a\u6703\u547d\u4e2d\u3002", "materials": [{"material": "\u59c6\u514b\u5152\u7684\u7fbd\u6bdb", "count": 3, "pm": "396"}, {"material": "\u5c0f\u7bad\u96c0\u7684\u7fbd\u6bdb", "count": 3, "pm": "661"}]}, {"TMPid": 32, "leaguePoint": 200, "pid": 129, "nameZh": "\u9ad8\u901f\u661f\u661f", "nameJp": "\u30b9\u30d4\u30fc\u30c9\u30b9\u30bf\u30fc", "nameEn": "Swift", "type": "\u4e00\u822c", "category": "\u7279\u6b8a", "power": 60, "accuracy": 0, "PP": 20, "description": "\u767c\u5c04\u661f\u578b\u5149\u7dda\u653b\u64ca\u5c0d\u624b\u3002\u653b\u64ca\u5fc5\u5b9a\u6703\u547d\u4e2d\u3002", "materials": [{"material": "\u5c0f\u7bad\u96c0\u7684\u7fbd\u6bdb", "count": 3, "pm": "661"}]}, {"TMPid": 38, "leaguePoint": 800, "pid": 488, "nameZh": "\u84c4\u80fd\u7130\u8972", "nameJp": "\u30cb\u30c8\u30ed\u30c1\u30e3\u30fc\u30b8", "nameEn": "Flame Charge", "type": "\u706b", "category": "\u7269\u7406", "power": 50, "accuracy": 100, "PP": 20, "description": "\u8b93\u706b\u7130\u570d\u7e5e\u5168\u8eab\u5f8c\u653b\u64ca\u5c0d\u624b\u3002\u540c\u6642\u84c4\u7a4d\u529b\u91cf\u4f86\u63d0\u9ad8\u81ea\u5df1\u7684\u901f\u5ea6\u3002", "materials": [{"material": "\u5c0f\u7bad\u96c0\u7684\u7fbd\u6bdb", "count": 3, "pm": "661"}, {"material": "\u7164\u70ad\u9f9c\u7684\u7164\u70ad", "count": 3, "pm": "324"}]}, {"TMPid": 40, "leaguePoint": 400, "pid": 314, "nameZh": "\u7a7a\u6c23\u5229\u5203", "nameJp": "\u30a8\u30a2\u30ab\u30c3\u30bf\u30fc", "nameEn": "Air Cutter", "type": "\u98db\u884c", "category": "\u7279\u6b8a", "power": 60, "accuracy": 95, "PP": 25, "description": "\u7528\u92d2\u5229\u7684\u98a8\u5203\u65ac\u5207\u5c0d\u624b\u9032\u884c\u653b\u64ca\u3002\u5bb9\u6613\u64ca\u4e2d\u8981\u5bb3\u3002", "materials": [{"material": "\u4e09\u871c\u8702\u7684\u871c", "count": 3, "pm": "415"}]}, {"TMPid": 47, "leaguePoint": 200, "pid": 203, "nameZh": "\u633a\u4f4f", "nameJp": "\u3053\u3089\u3048\u308b", "nameEn": "Endure", "type": "\u4e00\u822c", "category": "\u8b8a\u5316", "power": 0, "accuracy": 0, "PP": 10, "description": "\u5373\u4f7f\u53d7\u5230\u518d\u5f37\u70c8\u7684\u653b\u64ca\uff0c\u4e5f\u4e00\u5b9a\u6703\u5269\u4e0b\uff11\uff28\uff30\u3002\u9023\u7e8c\u4f7f\u7528\u6642\u5bb9\u6613\u5931\u6557\u3002", "materials": [{"material": "\u7c89\u8776\u87f2\u7684\u7c89", "count": 3, "pm": "664"}]}, {"TMPid": 49, "leaguePoint": 3000, "pid": 241, "nameZh": "\u5927\u6674\u5929", "nameJp": "\u306b\u307b\u3093\u3070\u308c", "nameEn": "Sunny Day", "type": "\u706b", "category": "\u8b8a\u5316", "power": 0, "accuracy": 0, "PP": 5, "description": "\u8b93\u967d\u5149\u589e\u5f37\uff0c\u5728\uff15\u56de\u5408\u5167\u63d0\u9ad8\u706b\u5c6c\u6027\u62db\u5f0f\u7684\u5a01\u529b\u3002\u6c34\u5c6c\u6027\u62db\u5f0f\u7684\u5a01\u529b\u6703\u964d\u4f4e\u3002", "materials": [{"material": "\u5411\u65e5\u7a2e\u5b50\u7684\u8449\u7247", "count": 3, "pm": "191"}, {"material": "\u7164\u70ad\u9f9c\u7684\u7164\u70ad", "count": 3, "pm": "324"}, {"material": "\u5c0f\u7345\u7345\u7684\u9b03\u6bdb", "count": 3, "pm": "667"}]}, {"TMPid": 50, "leaguePoint": 3000, "pid": 240, "nameZh": "\u6c42\u96e8", "nameJp": "\u3042\u307e\u3054\u3044", "nameEn": "Rain Dance", "type": "\u6c34", "category": "\u8b8a\u5316", "power": 0, "accuracy": 0, "PP": 5, "description": "\u964d\u4e0b\u5927\u96e8\uff0c\u5728\uff15\u56de\u5408\u5167\u63d0\u9ad8\u6c34\u5c6c\u6027\u62db\u5f0f\u7684\u5a01\u529b\u3002\u706b\u5c6c\u6027\u62db\u5f0f\u7684\u5a01\u529b\u6703\u964d\u4f4e\u3002", "materials": [{"material": "\u7121\u6bbc\u6d77\u5154\u7684\u9ecf\u6db2", "count": 3, "pm": "422"}, {"material": "\u9732\u529b\u9e97\u7684\u6bdb", "count": 3, "pm": "298"}, {"material": "\u96fb\u6d77\u71d5\u7684\u7fbd\u6bdb", "count": 3, "pm": "940"}]}, {"TMPid": 60, "leaguePoint": 3000, "pid": 369, "nameZh": "\u6025\u901f\u6298\u8fd4", "nameJp": "\u3068\u3093\u307c\u304c\u3048\u308a", "nameEn": "U-turn", "type": "\u87f2", "category": "\u7269\u7406", "power": 70, "accuracy": 100, "PP": 20, "description": "\u653b\u64ca\u5f8c\u8fc5\u901f\u8fd4\u56de\uff0c\u548c\u5f8c\u5099\u5bf6\u53ef\u5922\u9032\u884c\u66ff\u63db\u3002", "materials": [{"material": "\u8c46\u87cb\u87c0\u7684\u722a\u5b50", "count": 3, "pm": "919"}, {"material": "\u98db\u5929\u87b3\u8782\u7684\u722a\u5b50", "count": 3, "pm": "123"}]}, {"TMPid": 65, "leaguePoint": 5000, "pid": 403, "nameZh": "\u7a7a\u6c23\u65ac", "nameJp": "\u30a8\u30a2\u30b9\u30e9\u30c3\u30b7\u30e5", "nameEn": "Air Slash", "type": "\u98db\u884c", "category": "\u7279\u6b8a", "power": 75, "accuracy": 95, "PP": 15, "description": "\u7528\u9023\u5929\u7a7a\u4e5f\u80fd\u5288\u958b\u7684\u7a7a\u6c23\u65ac\u9032\u884c\u653b\u64ca\u3002\u6709\u6642\u6703\u4f7f\u5c0d\u624b\u754f\u7e2e\u3002", "materials": [{"material": "\u55e1\u8760\u7684\u6bdb", "count": 3, "pm": "714"}, {"material": "\u9577\u7fc5\u9dd7\u7684\u7fbd\u6bdb", "count": 3, "pm": "278"}, {"material": "\u7e8f\u7d05\u9db4\u7684\u7fbd\u7d68", "count": 3, "pm": "973"}]}, {"TMPid": 70, "leaguePoint": 400, "pid": 214, "nameZh": "\u5922\u8a71", "nameJp": "\u306d\u3054\u3068", "nameEn": "Sleep Talk", "type": "\u4e00\u822c", "category": "\u8b8a\u5316", "power": 0, "accuracy": 0, "PP": 10, "description": "\u5f9e\u81ea\u5df1\u5df2\u5b78\u6703\u7684\u62db\u5f0f\u4e2d\u96a8\u6a5f\u9078\u51fa\uff11\u500b\u4f7f\u51fa\u3002\u53ea\u6709\u5728\u7761\u7720\u72c0\u614b\u6642\u53ef\u4ee5\u4f7f\u7528\u3002", "materials": [{"material": "\u6c99\u6cb3\u99ac\u7684\u6c99", "count": 3, "pm": "449"}, {"material": "\u5446\u5446\u7378\u7684\u722a\u5b50", "count": 3, "pm": "79"}]}, {"TMPid": 85, "leaguePoint": 400, "pid": 156, "nameZh": "\u7761\u89ba", "nameJp": "\u306d\u3080\u308b", "nameEn": "Rest", "type": "\u8d85\u80fd\u529b", "category": "\u8b8a\u5316", "power": 0, "accuracy": 0, "PP": 5, "description": "\u9023\u7e8c\u7761\uff12\u56de\u5408\u3002\u56de\u5fa9\u81ea\u5df1\u7684\u5168\u90e8\uff28\uff30\u4ee5\u53ca\u6cbb\u7652\u6240\u6709\u7570\u5e38\u72c0\u614b\u3002", "materials": [{"material": "\u50ac\u7720\u8c98\u7684\u6bdb", "count": 3, "pm": "96"}]}, {"TMPid": 87, "leaguePoint": 3000, "pid": 269, "nameZh": "\u6311\u91c1", "nameJp": "\u3061\u3087\u3046\u306f\u3064", "nameEn": "Taunt", "type": "\u60e1", "category": "\u8b8a\u5316", "power": 0, "accuracy": 100, "PP": 20, "description": "\u6fc0\u6012\u5c0d\u624b\u3002\u5728\uff13\u56de\u5408\u5167\u8b93\u5c0d\u624b\u53ea\u80fd\u4f7f\u51fa\u7d66\u4e88\u50b7\u5bb3\u7684\u62db\u5f0f\u3002", "materials": [{"material": "\u55b5\u55b5\u7684\u6bdb", "count": 3, "pm": "52"}, {"material": "\u52fe\u9b42\u773c\u7684\u5bf6\u77f3", "count": 3, "pm": "302"}, {"material": "\u72c3\u62c9\u7684\u722a\u5b50", "count": 3, "pm": "215"}]}, {"TMPid": 88, "leaguePoint": 5000, "pid": 14, "nameZh": "\u528d\u821e", "nameJp": "\u3064\u308b\u304e\u306e\u307e\u3044", "nameEn": "Swords Dance", "type": "\u4e00\u822c", "category": "\u8b8a\u5316", "power": 0, "accuracy": 0, "PP": 20, "description": "\u6fc0\u70c8\u5730\u8df3\u8d77\u6230\u821e\u63d0\u5347\u6c23\u52e2\u3002\u5927\u5e45\u63d0\u9ad8\u81ea\u5df1\u7684\u653b\u64ca\u3002", "materials": [{"material": "\u8c93\u9f2c\u65ac\u7684\u722a\u5b50", "count": 3, "pm": "335"}, {"material": "\u5713\u9678\u9bca\u7684\u9c57\u7247", "count": 3, "pm": "443"}, {"material": "\u98db\u5929\u87b3\u8782\u7684\u722a\u5b50", "count": 3, "pm": "123"}]}, {"TMPid": 97, "leaguePoint": 5000, "pid": 19, "nameZh": "\u98db\u7fd4", "nameJp": "\u305d\u3089\u3092\u3068\u3076", "nameEn": "Fly", "type": "\u98db\u884c", "category": "\u7269\u7406", "power": 90, "accuracy": 95, "PP": 15, "description": "\u4f7f\u7528\u5f8c\u7684\u7b2c\uff11\u56de\u5408\u98db\u4e0a\u5929\u7a7a\uff0c\u4e26\u65bc\u7b2c\uff12\u56de\u5408\u653b\u64ca\u5c0d\u624b\u3002", "materials": [{"material": "\u6012\u9e1a\u54e5\u7684\u7fbd\u6bdb", "count": 3, "pm": "931"}, {"material": "\u4e0b\u77f3\u9ce5\u7684\u7fbd\u6bdb", "count": 3, "pm": "962"}, {"material": "\u6bdb\u982d\u5c0f\u9df9\u7684\u7fbd\u6bdb", "count": 3, "pm": "627"}]}, {"TMPid": 103, "leaguePoint": 5000, "pid": 164, "nameZh": "\u66ff\u8eab", "nameJp": "\u307f\u304c\u308f\u308a", "nameEn": "Substitute", "type": "\u4e00\u822c", "category": "\u8b8a\u5316", "power": 0, "accuracy": 0, "PP": 10, "description": "\u6d88\u8017\u4e00\u4e9b\u81ea\u5df1\u7684\uff28\uff30\uff0c\u88fd\u9020\u5206\u8eab\u3002\u5206\u8eab\u5c07\u6210\u70ba\u81ea\u5df1\u7684\u66ff\u8eab\u3002", "materials": [{"material": "\u8b0e\u64ec\uff31\u7684\u6b98\u7247", "count": 3, "pm": "778"}, {"material": "\u9732\u529b\u9e97\u7684\u6bdb", "count": 3, "pm": "298"}, {"material": "\u5217\u9663\u5175\u7684\u6c57", "count": 3, "pm": "870"}]}, {"TMPid": 107, "leaguePoint": 3000, "pid": 261, "nameZh": "\u9b3c\u706b", "nameJp": "\u304a\u306b\u3073", "nameEn": "Will-O-Wisp", "type": "\u706b", "category": "\u8b8a\u5316", "power": 0, "accuracy": 85, "PP": 15, "description": "\u653e\u51fa\u8a6d\u7570\u7684\u706b\u7130\uff0c\u8b93\u5c0d\u624b\u9677\u5165\u707c\u50b7\u72c0\u614b\u3002", "materials": [{"material": "\u591c\u76dc\u706b\u8725\u7684\u6c23\u9ad4", "count": 3, "pm": "757"}, {"material": "\u6028\u5f71\u5a03\u5a03\u7684\u788e\u7247", "count": 3, "pm": "353"}]}, {"TMPid": 113, "leaguePoint": 5000, "pid": 366, "nameZh": "\u9806\u98a8", "nameJp": "\u304a\u3044\u304b\u305c", "nameEn": "Tailwind", "type": "\u98db\u884c", "category": "\u8b8a\u5316", "power": 0, "accuracy": 0, "PP": 15, "description": "\u522e\u8d77\u731b\u70c8\u7684\u5f37\u98a8\uff0c\u5728\uff14\u56de\u5408\u5167\u63d0\u9ad8\u6211\u65b9\u5168\u9ad4\u7684\u901f\u5ea6\u3002", "materials": [{"material": "\u6bdb\u982d\u5c0f\u9df9\u7684\u7fbd\u6bdb", "count": 3, "pm": "627"}, {"material": "\u7a1a\u5c71\u96c0\u7684\u7fbd\u6bdb", "count": 3, "pm": "821"}, {"material": "\u4e0b\u77f3\u9ce5\u7684\u7fbd\u6bdb", "count": 3, "pm": "962"}]}, {"TMPid": 118, "leaguePoint": 10000, "pid": 257, "nameZh": "\u71b1\u98a8", "nameJp": "\u306d\u3063\u3077\u3046", "nameEn": "Heat Wave", "type": "\u706b", "category": "\u7279\u6b8a", "power": 95, "accuracy": 90, "PP": 10, "description": "\u5c07\u708e\u71b1\u7684\u6c23\u606f\u5439\u5411\u5c0d\u624b\u9032\u884c\u653b\u64ca\u3002\u6709\u6642\u6703\u8b93\u5c0d\u624b\u9677\u5165\u707c\u50b7\u72c0\u614b\u3002", "materials": [{"material": "\u5361\u8482\u72d7\u7684\u6bdb", "count": 5, "pm": "58"}, {"material": "\u7164\u70ad\u9f9c\u7684\u7164\u70ad", "count": 3, "pm": "324"}, {"material": "\u71c3\u71d2\u87f2\u7684\u6bdb", "count": 3, "pm": "636"}]}, {"TMPid": 125, "leaguePoint": 10000, "pid": 53, "nameZh": "\u5674\u5c04\u706b\u7130", "nameJp": "\u304b\u3048\u3093\u307b\u3046\u3057\u3083", "nameEn": "Flamethrower", "type": "\u706b", "category": "\u7279\u6b8a", "power": 90, "accuracy": 100, "PP": 15, "description": "\u5411\u5c0d\u624b\u767c\u5c04\u5f37\u70c8\u706b\u7130\u9032\u884c\u653b\u64ca\u3002\u6709\u6642\u6703\u8b93\u5c0d\u624b\u9677\u5165\u707c\u50b7\u72c0\u614b\u3002", "materials": [{"material": "\u5c0f\u7345\u7345\u7684\u9b03\u6bdb", "count": 5, "pm": "667"}, {"material": "\u6234\u9b6f\u6bd4\u7684\u7259", "count": 3, "pm": "228"}, {"material": "\u5446\u706b\u99dd\u7684\u7194\u5ca9", "count": 3, "pm": "322"}]}, {"TMPid": 141, "leaguePoint": 12000, "pid": 126, "nameZh": "\u5927\u5b57\u7206\u708e", "nameJp": "\u3060\u3044\u3082\u3093\u3058", "nameEn": "Fire Blast", "type": "\u706b", "category": "\u7279\u6b8a", "power": 110, "accuracy": 85, "PP": 5, "description": "\u7528\u5927\u5b57\u5f62\u72c0\u7684\u706b\u7130\u71d2\u76e1\u5c0d\u624b\u3002\u6709\u6642\u6703\u8b93\u5c0d\u624b\u9677\u5165\u707c\u50b7\u72c0\u614b\u3002", "materials": [{"material": "\u5446\u706b\u99dd\u7684\u7194\u5ca9", "count": 5, "pm": "322"}, {"material": "\u71c3\u71d2\u87f2\u7684\u6bdb", "count": 3, "pm": "636"}, {"material": "\u7164\u70ad\u9f9c\u7684\u7164\u70ad", "count": 3, "pm": "324"}]}, {"TMPid": 157, "leaguePoint": 12000, "pid": 315, "nameZh": "\u904e\u71b1", "nameJp": "\u30aa\u30fc\u30d0\u30fc\u30d2\u30fc\u30c8", "nameEn": "Overheat", "type": "\u706b", "category": "\u7279\u6b8a", "power": 130, "accuracy": 90, "PP": 5, "description": "\u91cb\u653e\u5168\u90e8\u80fd\u91cf\u653b\u64ca\u5c0d\u624b\u3002\u4f7f\u7528\u5f8c\u56e0\u70ba\u53cd\u4f5c\u7528\u529b\uff0c\u81ea\u5df1\u7684\u7279\u653b\u6703\u5927\u5e45\u964d\u4f4e\u3002", "materials": [{"material": "\u5c0f\u7345\u7345\u7684\u9b03\u6bdb", "count": 5, "pm": "667"}, {"material": "\u5446\u706b\u99dd\u7684\u7194\u5ca9", "count": 3, "pm": "322"}, {"material": "\u71b1\u8fa3\u5a03\u7684\u7a2e\u5b50", "count": 3, "pm": "951"}]}, {"TMPid": 160, "leaguePoint": 12000, "pid": 542, "nameZh": "\u66b4\u98a8", "nameJp": "\u307c\u3046\u3075\u3046", "nameEn": "Hurricane", "type": "\u98db\u884c", "category": "\u7279\u6b8a", "power": 110, "accuracy": 70, "PP": 10, "description": "\u7528\u5f37\u70c8\u7684\u98a8\u5e2d\u6372\u5c0d\u624b\u9032\u884c\u653b\u64ca\u3002\u6709\u6642\u6703\u4f7f\u5c0d\u624b\u6df7\u4e82\u3002", "materials": [{"material": "\u9752\u7dbf\u9ce5\u7684\u7fbd\u6bdb", "count": 5, "pm": "333"}, {"material": "\u82b1\u821e\u9ce5\u7684\u7fbd\u6bdb", "count": 3, "pm": "741"}, {"material": "\u9577\u7fc5\u9dd7\u7684\u7fbd\u6bdb", "count": 3, "pm": "278"}]}, {"TMPid": 164, "leaguePoint": 12000, "pid": 413, "nameZh": "\u52c7\u9ce5\u731b\u653b", "nameJp": "\u30d6\u30ec\u30a4\u30d6\u30d0\u30fc\u30c9", "nameEn": "Brave Bird", "type": "\u98db\u884c", "category": "\u7269\u7406", "power": 120, "accuracy": 100, "PP": 15, "description": "\u6536\u8d77\u7fc5\u8180\uff0c\u4f4e\u7a7a\u98db\u884c\u7a81\u64ca\u5c0d\u624b\u3002\u81ea\u5df1\u4e5f\u6703\u53d7\u5230\u4e0d\u5c0f\u7684\u50b7\u5bb3\u3002", "materials": [{"material": "\u59c6\u514b\u5152\u7684\u7fbd\u6bdb", "count": 5, "pm": "396"}, {"material": "\u6bdb\u982d\u5c0f\u9df9\u7684\u7fbd\u6bdb", "count": 3, "pm": "627"}, {"material": "\u7a1a\u5c71\u96c0\u7684\u7fbd\u6bdb", "count": 3, "pm": "821"}]}, {"TMPid": 165, "leaguePoint": 12000, "pid": 394, "nameZh": "\u9583\u7130\u885d\u92d2", "nameJp": "\u30d5\u30ec\u30a2\u30c9\u30e9\u30a4\u30d6", "nameEn": "Flare Blitz", "type": "\u706b", "category": "\u7269\u7406", "power": 120, "accuracy": 100, "PP": 15, "description": "\u5c07\u706b\u7130\u570d\u7e5e\u5168\u8eab\u5f8c\u731b\u649e\u5c0d\u624b\u3002\u81ea\u5df1\u4e5f\u6703\u53d7\u5230\u4e0d\u5c0f\u7684\u50b7\u5bb3\u3002\u6709\u6642\u6703\u8b93\u5c0d\u624b\u9677\u5165\u707c\u50b7\u72c0\u614b\u3002", "materials": [{"material": "\u5361\u8482\u72d7\u7684\u6bdb", "count": 5, "pm": "58"}, {"material": "\u5c0f\u7bad\u96c0\u7684\u7fbd\u6bdb", "count": 3, "pm": "661"}, {"material": "\u70ad\u5c0f\u4f8d\u7684\u7164\u7070", "count": 3, "pm": "935"}]}, {"TMPid": 171, "leaguePoint": 8000, "pid": 851, "nameZh": "\u592a\u6676\u7206\u767c", "nameJp": "\u30c6\u30e9\u30d0\u30fc\u30b9\u30c8", "nameEn": "Tera Blast", "type": "\u4e00\u822c", "category": "\u7279\u6b8a", "power": 80, "accuracy": 100, "PP": 10, "description": "\u82e5\u662f\u5728\u592a\u6676\u5316\u6642\uff0c\u5c07\u91cb\u653e\u592a\u6676\u5c6c\u6027\u7684\u80fd\u91cf\u9032\u884c\u653b\u64ca\u3002\u6703\u6bd4\u8f03\u81ea\u5df1\u7684\u653b\u64ca\u548c\u7279\u653b\uff0c\u4ee5\u6578\u503c\u8f03\u9ad8\u7684\u4e00\u65b9\u9032\u884c\u653b\u64ca\u3002", "materials": [{"material": "\u6676\u5149\u82bd\u7684\u7d50\u6676", "count": 8, "pm": "969"}]}, {"TMPid": 197, "leaguePoint": 5000, "pid": 814, "nameZh": "\u96d9\u7ffc", "nameJp": "\u30c0\u30d6\u30eb\u30a6\u30a4\u30f3\u30b0", "nameEn": "Dual Wingbeat", "type": "\u98db\u884c", "category": "\u7269\u7406", "power": 40, "accuracy": 90, "PP": 10, "description": "\u7528\u7fc5\u8180\u649e\u5411\u5c0d\u624b\u9032\u884c\u653b\u64ca\u3002\u9023\u7e8c\uff12\u6b21\u7d66\u4e88\u50b7\u5bb3\u3002", "materials": [{"material": "\u4e0b\u77f3\u9ce5\u7684\u7fbd\u6bdb\u00a0", "count": 3, "pm": "962"}, {"material": "\u9d28\u5bf6\u5bf6\u7684\u7fbd\u6bdb\u00a0", "count": 3, "pm": "580"}]}]}, "evolves": [{"from": "661", "to": "662", "fromNameZh": "\u5c0f\u7bad\u96c0", "toNameZh": "\u706b\u7bad\u96c0", "condition": "lv17", "evolves": [{"from": "662", "to": "663", "fromNameZh": "\u706b\u7bad\u96c0", "toNameZh": "\u70c8\u7bad\u9df9", "condition": "lv35"}]}]}